Docker/__init__.py
Docker/__main__.py
Docker/application.py
Docker/container.py
Docker/docker.py
docker_unite-0.1.2.dist-info/METADATA
docker_unite-0.1.2.dist-info/WHEEL
docker_unite-0.1.2.dist-info/entry_points.txt
docker_unite-0.1.2.dist-info/licenses/LICENSE
docker_unite-0.1.2.dist-info/RECORD
