Metadata-Version: 2.4
Name: docker-unite
Version: 0.1.2
Summary: Manage multiple docker containers in one place.
Project-URL: Homepage, https://gitlab.com/0tanay/docker
Project-URL: Repository, https://gitlab.com/0tanay/docker.git
Project-URL: Issues, https://gitlab.com/0tanay/docker/-/issues
License-File: LICENSE
Requires-Dist: click
Requires-Dist: docker
